python_camellia-0.1.1.dist-info/metadata.json
python_camellia-0.1.1.dist-info/RECORD
python_camellia-0.1.1.dist-info/top_level.txt
python_camellia-0.1.1.dist-info/METADATA
python_camellia-0.1.1.dist-info/DESCRIPTION.rst
python_camellia-0.1.1.dist-info/WHEEL
camellia/__main__.py
camellia/camellia-win32-x86-WindowsPE.dll
camellia/__init__.py
camellia/camellia-win32-AMD64-WindowsPE.dll
camellia/camellia.c
