Metadata-Version: 2.0
Name: python-camellia
Version: 0.1.1
Summary: Camellia-cipher in Python
Home-page: https://github.com/var-sec/python-camellia
Author: Simon Biewald
Author-email: simon.biewald@homtail.de
License: MIT
Keywords: camellia,encryption,decryption,cipher
Platform: all
Platform: gcc
Classifier: Development Status :: 3 - Alpha
Classifier: Intended Audience :: Developers
Classifier: License :: OSI Approved :: MIT License
Classifier: Programming Language :: Python
Classifier: Programming Language :: Python :: 2
Classifier: Programming Language :: Python :: 3
Classifier: Programming Language :: Python :: Implementation :: CPython
Classifier: Programming Language :: Python :: Implementation :: PyPy
Classifier: Topic :: Security
Classifier: Topic :: Security :: Cryptography
